flask_script_extras/__init__.py
Flask_Script_Extras-0.1.4.dist-info/DESCRIPTION.rst
Flask_Script_Extras-0.1.4.dist-info/METADATA
Flask_Script_Extras-0.1.4.dist-info/metadata.json
Flask_Script_Extras-0.1.4.dist-info/RECORD
Flask_Script_Extras-0.1.4.dist-info/top_level.txt
Flask_Script_Extras-0.1.4.dist-info/WHEEL
